mqtt_presence/__init__.py
mqtt_presence/__main__.py
mqtt_presence/config/config_handler.py
mqtt_presence/config/configuration.py
mqtt_presence/devices/device.py
mqtt_presence/devices/device_data.py
mqtt_presence/devices/devices.py
mqtt_presence/devices/pc_utils/pc_utils.py
mqtt_presence/devices/pc_utils/pc_utils_data.py
mqtt_presence/devices/raspberrypi/raspberrypi_data.py
mqtt_presence/devices/raspberrypi/raspberrypi_device.py
mqtt_presence/devices/raspberrypi/raspberrypi_gpio_handler.py
mqtt_presence/main.py
mqtt_presence/mqtt/mqtt_client.py
mqtt_presence/mqtt_presence_app.py
mqtt_presence/parser.py
mqtt_presence/static/bootstrap/css/bootstrap.min.css
mqtt_presence/static/bootstrap/js/bootstrap.bundle.min.js
mqtt_presence/static/img/favicon.png
mqtt_presence/static/img/logo.png
mqtt_presence/static/js/vue.global.js
mqtt_presence/static/js/vue.global.prod.js
mqtt_presence/static/materialdesignicons/css/materialdesignicons.min.css
mqtt_presence/static/materialdesignicons/fonts/materialdesignicons-webfont.eot
mqtt_presence/static/materialdesignicons/fonts/materialdesignicons-webfont.ttf
mqtt_presence/static/materialdesignicons/fonts/materialdesignicons-webfont.woff
mqtt_presence/static/materialdesignicons/fonts/materialdesignicons-webfont.woff2
mqtt_presence/static/materialdesignicons/fonts/materialdesignicons.min.css.map
mqtt_presence/templates/index_vue.html
mqtt_presence/templates/tab_appconfig.html
mqtt_presence/templates/tab_mqtt.html
mqtt_presence/templates/tab_pcutils.html
mqtt_presence/templates/tab_raspberrypi/tab_raspberrypi.html
mqtt_presence/templates/tab_raspberrypi/tab_raspberrypi_config.html
mqtt_presence/templates/tab_raspberrypi/tab_raspberrypi_status.html
mqtt_presence/utils.py
mqtt_presence/version.py
mqtt_presence/web_ui_vue.py
mqtt_presence-0.2.9.dist-info/entry_points.txt
mqtt_presence-0.2.9.dist-info/LICENSE
mqtt_presence-0.2.9.dist-info/METADATA
mqtt_presence-0.2.9.dist-info/WHEEL
mqtt_presence-0.2.9.dist-info/RECORD
