Metadata-Version: 2.3
Name: mqtt-presence
Version: 0.2.9
Summary: Lightweight MQTT-based presence detection with shutdown and Raspberry Pi GPio support
License: Apache-2.0
Keywords: mqtt,presence,shutdown,home-assistant,smart-home,mqtt-discovery,mqtt-client,mqtt-online,mqtt-online-state,gpio,raspberrypi-gpio
Author: Bjoern Boeckle
Author-email: bjoern@boeckle-net.de
Requires-Python: >=3.11,<4.0
Classifier: License :: OSI Approved :: Apache Software License
Classifier: Programming Language :: Python :: 3
Classifier: Programming Language :: Python :: 3.11
Classifier: Programming Language :: Python :: 3.12
Classifier: Programming Language :: Python :: 3.13
Requires-Dist: RPi.GPIO ; platform_system == "Linux" and (platform_machine == "armv7l" or platform_machine == "aarch64")
Requires-Dist: cryptography
Requires-Dist: dacite (>=1.8.1,<2.0.0)
Requires-Dist: flask
Requires-Dist: gpiozero ; platform_system == "Linux" and (platform_machine == "armv7l" or platform_machine == "aarch64")
Requires-Dist: paho-mqtt
Requires-Dist: platformdirs
Requires-Dist: psutil
Requires-Dist: requests
Requires-Dist: rpi-lgpio ; platform_system == "Linux" and (platform_machine == "armv7l" or platform_machine == "aarch64")
Requires-Dist: ruamel.yaml (>=0.18.6,<0.19.0)
Requires-Dist: waitress
Project-URL: Documentation, https://github.com/bjoernboeckle/mqtt-presence/wiki
Project-URL: Repository, https://github.com/bjoernboeckle/mqtt-presence
